letra/__init__.py
letra/_helpers.py
letra/_parser.py
letra/exceptions.py
letra/label.py
letra/letra.py
letra/version.py
letra/_file_io/__init__.py
letra/_file_io/file_io.py
letra/_file_io/template_file_format.py
letra/_file_io/yaml.py
letra/_label_platform_provider/__init__.py
letra/_label_platform_provider/github.py
letra/_label_platform_provider/github_helpers.py
letra/_label_platform_provider/http_helpers.py
letra/_label_platform_provider/label_platform_provider.py
tests/__init__.py
tests/helpers.py
tests/unit/__init__.py
tests/unit/test_exceptions.py
tests/unit/test_helpers.py
tests/unit/test_label.py
tests/unit/test_letra.py
tests/unit/test_parser.py
letra-0.5.1.dist-info/LICENSE
letra-0.5.1.dist-info/METADATA
letra-0.5.1.dist-info/WHEEL
letra-0.5.1.dist-info/top_level.txt
letra-0.5.1.dist-info/RECORD
