Metadata-Version: 2.1
Name: letra
Version: 0.5.1
Summary: Utility for managing GitHub issue labels
Home-page: https://github.com/swellaby/letra
Author: Swellaby
Author-email: opensource@swellaby.com
License: MIT
Platform: UNKNOWN
Classifier: Development Status :: 2 - Pre-Alpha
Classifier: Programming Language :: Python :: 3 :: Only
Classifier: Programming Language :: Python :: 3.6
Classifier: Programming Language :: Python :: 3.7
Classifier: Programming Language :: Python :: 3.8
Classifier: License :: OSI Approved :: MIT License
Classifier: Operating System :: OS Independent
